shui/__init__.py
shui/classes/__init__.py
shui/classes/file_with_hash.py
shui/classes/fileinfo.py
shui/classes/version.py
shui/cli.py
shui/commands/__init__.py
shui/commands/install_command.py
shui/commands/versions_command.py
shui/functions/__init__.py
shui/functions/file_details.py
shui/functions/install.py
shui/functions/response.py
shui/functions/versions.py
shui-0.8.1.dist-info/LICENSE
shui-0.8.1.dist-info/METADATA
shui-0.8.1.dist-info/WHEEL
shui-0.8.1.dist-info/entry_points.txt
shui-0.8.1.dist-info/RECORD
