Metadata-Version: 2.1
Name: shui
Version: 0.8.1
Summary: Spark-Hadoop Unix Installer
Home-page: https://github.com/jemrobinson/shui
License: MIT
Keywords: Spark,Hadoop,installation
Author: James Robinson
Author-email: james.em.robinson@gmail.com
Requires-Python: >=3.8,<4.0
Classifier: Development Status :: 3 - Alpha
Classifier: Environment :: Console
Classifier: Intended Audience :: End Users/Desktop
Classifier: License :: OSI Approved :: MIT License
Classifier: Natural Language :: English
Classifier: Operating System :: Unix
Classifier: Programming Language :: Python :: 3
Classifier: Programming Language :: Python :: 3.8
Classifier: Programming Language :: Python :: 3.9
Classifier: Programming Language :: Python :: 3.10
Classifier: Programming Language :: Python :: 3.11
Classifier: Programming Language :: Python :: 3.12
Classifier: Topic :: Software Development
Classifier: Topic :: Utilities
Requires-Dist: beautifulsoup4 (>=4.12)
Requires-Dist: cleo (>=2.0)
Requires-Dist: importlib-metadata (>=6.7) ; python_version < "3.8"
Requires-Dist: packaging (>=23.0)
Requires-Dist: pathlib3x (>=2.0)
Requires-Dist: requests (>=2.31)
Requires-Dist: tqdm (>=4.66)
Requires-Dist: url-normalize (>=1.4)
Requires-Dist: urllib3 (>=2.0)
Project-URL: Repository, https://github.com/jemrobinson/shui
